fortnitesave/__init__.py
fortnitesave/auth.py
fortnitesave/avatar.py
fortnitesave/client.py
fortnitesave/enums.py
fortnitesave/errors.py
fortnitesave/friend.py
fortnitesave/http.py
fortnitesave/message.py
fortnitesave/news.py
fortnitesave/party.py
fortnitesave/playlist.py
fortnitesave/presence.py
fortnitesave/stats.py
fortnitesave/store.py
fortnitesave/typedefs.py
fortnitesave/user.py
fortnitesave/utils.py
fortnitesave/xmpp.py
fortnitesave/ext/commands/__init__.py
fortnitesave/ext/commands/_types.py
fortnitesave/ext/commands/bot.py
fortnitesave/ext/commands/cog.py
fortnitesave/ext/commands/context.py
fortnitesave/ext/commands/converter.py
fortnitesave/ext/commands/cooldown.py
fortnitesave/ext/commands/core.py
fortnitesave/ext/commands/errors.py
fortnitesave/ext/commands/help.py
fortnitesave/ext/commands/typedefs.py
fortnitesave/ext/commands/view.py
fortnitesave-3.7.0.dist-info/LICENSE
fortnitesave-3.7.0.dist-info/METADATA
fortnitesave-3.7.0.dist-info/WHEEL
fortnitesave-3.7.0.dist-info/top_level.txt
fortnitesave-3.7.0.dist-info/RECORD
