Metadata-Version: 2.1
Name: fortnitesave
Version: 3.7.0
Summary: Library for interacting with fortnite services
Home-page: UNKNOWN
Author: saver
License: MIT
Platform: UNKNOWN
Classifier: License :: OSI Approved :: MIT License
Classifier: Intended Audience :: Developers
Classifier: Natural Language :: English
Classifier: Operating System :: OS Independent
Classifier: Programming Language :: Python :: 3.5
Classifier: Programming Language :: Python :: 3.6
Classifier: Programming Language :: Python :: 3.7
Classifier: Programming Language :: Python :: 3.8
Classifier: Programming Language :: Python :: 3.9
Classifier: Programming Language :: Python :: 3.10
Classifier: Topic :: Internet
Classifier: Topic :: Software Development :: Libraries
Classifier: Topic :: Software Development :: Libraries :: Python Modules
Classifier: Topic :: Utilities
Requires-Python: >=3.5.3
Requires-Dist: aioconsole (>=0.1.15)
Requires-Dist: aiohttp (>=3.3)
Requires-Dist: aioxmpp (>=0.13.2)
Provides-Extra: docs
Requires-Dist: Jinja2 (<3.1) ; extra == 'docs'
Requires-Dist: furo (==2021.4.11b34) ; extra == 'docs'
Requires-Dist: sphinxcontrib-trio (==1.1.2) ; extra == 'docs'
